modelgen/__init__.py
modelgen/alembic.ini
modelgen/base.py
modelgen/constants.py
modelgen/helper.py
modelgen/log_source.py
modelgen/main.py
modelgen/modelgenerator.py
modelgen/parser.py
modelgen/alembic_migrate/README
modelgen/alembic_migrate/__init__.py
modelgen/alembic_migrate/env.py
modelgen/alembic_migrate/script.py.mako
modelgen/alembic_migrate/versions/__init__.py
modelgen/templates/__init__.py
modelgen/templates/alchemygen.py
modelgen/templates/example.yaml
modelgen/templates/userinfo.yaml
modelgen/validator/__init__.py
modelgen/validator/schema.py
alchemy_modelgen-0.1.6.1.dist-info/LICENSE
alchemy_modelgen-0.1.6.1.dist-info/METADATA
alchemy_modelgen-0.1.6.1.dist-info/WHEEL
alchemy_modelgen-0.1.6.1.dist-info/entry_points.txt
alchemy_modelgen-0.1.6.1.dist-info/top_level.txt
alchemy_modelgen-0.1.6.1.dist-info/RECORD
