Metadata-Version: 2.1
Name: alchemy-modelgen
Version: 0.1.6.1
Summary: UNKNOWN
Home-page: https://github.com/shree14/sqlalchemy-modelgen
Author: Shrinivas Deshmukh
Author-email: shrinivas.deshmukh11@gmail.com
License: UNKNOWN
Platform: UNKNOWN
Requires-Dist: alembic (>=1.5.8)
Requires-Dist: Cerberus (>=1.3.3)
Requires-Dist: inflect
Requires-Dist: Jinja2 (>=2.11.3)
Requires-Dist: mysql-connector-python (>=8.0.23)
Requires-Dist: psycopg2-binary (>=2.8.6)
Requires-Dist: python-dotenv (>=0.17.0)
Requires-Dist: PyYAML (>=5.4.1)
Requires-Dist: snowflake-sqlalchemy (>=1.2.4)
Requires-Dist: sqlacodegen (>=2.3.0)
Requires-Dist: SQLAlchemy (==1.3.19)
Requires-Dist: sqlalchemy-redshift (>=0.8.2)
